giles/__init__.py
giles_athenaeum-0.0.1.dist-info/METADATA
giles_athenaeum-0.0.1.dist-info/RECORD
giles_athenaeum-0.0.1.dist-info/WHEEL
giles_athenaeum-0.0.1.dist-info/top_level.txt
